[
  {
    "ParameterKey": "SchedulerName",
    "ParameterValue": "dynamodbpoc-cleanup"
  },
  {
    "ParameterKey": "ScheduleExpressionUtc",
    "ParameterValue": "cron(30 7 * * ? *)"
  },
  {
    "ParameterKey": "StackPrefix",
    "ParameterValue": "dynamodb-poc"
  },
  {
    "ParameterKey": "StackNamesCsv",
    "ParameterValue": ""
  },
  {
    "ParameterKey": "ExcludeStacksCsv",
    "ParameterValue": "bedrock-agent-stack"
  },
  {
    "ParameterKey": "DryRun",
    "ParameterValue": "true"
  }
]
